<menus xmlns:MMString="http://www.macromedia.com/schemes/data/string/"><menuitem name="xxx" file="Menus/MM/Asset_Context_Refresh.htm" dynamic="true" /><menuitem name="_Edit" command="dw.assetPalette.edit()" enabled="(site.getSites().length > 0) && dw.assetPalette.canEdit()" id="DWContext_Assets_Edit" /><menuitem name="Edit _Original" file="Menus/MM/SmartObject_ContextMenuItem_AssetPanel_Edit_Original.htm" id="DWContext_Assets_Edit_Original" /><menuitem name="_Insert" file="Menus/MM/Asset_Context_Insert.htm" id="DWContext_Assets_Insert" /><menuitem name="_Update From Original" file="Menus/MM/SmartObject_ContextMenuItem_AssetPanel.htm" id="DWContext_Assets_UpdateFromOriginal" /><separator /><menuitem name="xxx" file="Menus/MM/Asset_Context_Nickname.htm" dynamic="true" /><separator /><menu name="_Copy to Site" id="DWContext_Assets_CopyToSite"></menu><menuitem name="_Locate in Site" command="dw.assetPalette.locateInSite()" enabled="(site.getSites().length > 0) && (dw.assetPalette.getSelectedCategory() != 'colors') && (dw.assetPalette.getSelectedCategory() != 'urls')" id="DWContext_Assets_LocateInSite" />